blindfold/__init__.py
blindfold/client.py
blindfold/errors.py
blindfold/models.py
blindfold/py.typed
blindfold_sdk-1.0.0.dist-info/METADATA
blindfold_sdk-1.0.0.dist-info/WHEEL
blindfold_sdk-1.0.0.dist-info/RECORD
